parallax_ai/__init__.py
parallax_ai/composer.py
parallax_ai/datapool.py
parallax_ai/distributor.py
parallax_ai/service.py
parallax_ai/utilities.py
parallax_ai/api_server/__init__.py
parallax_ai/api_server/hf_model_server.py
parallax_ai/api_server/hf_model_server_clean.py
parallax_ai/benchmarks/__init__.py
parallax_ai/benchmarks/safety_benchmarks/__init__.py
parallax_ai/benchmarks/safety_benchmarks/base_bench.py
parallax_ai/benchmarks/safety_benchmarks/metrics.py
parallax_ai/benchmarks/safety_benchmarks/collections/__init__.py
parallax_ai/benchmarks/safety_benchmarks/collections/pku_saferlhf_qa.py
parallax_ai/benchmarks/safety_benchmarks/collections/sea_safeguard_bench.py
parallax_ai/benchmarks/safety_benchmarks/collections/seals_bench.py
parallax_ai/builtin_agents/__init__.py
parallax_ai/builtin_agents/moe_safeguard.py
parallax_ai/builtin_agents/safeguard.py
parallax_ai/dataclasses/__init__.py
parallax_ai/dataclasses/instance.py
parallax_ai/dataclasses/job.py
parallax_ai/modules/__init__.py
parallax_ai/modules/agent_module.py
parallax_ai/modules/base_module.py
parallax_ai/modules/classification_module.py
parallax_ai/modules/lambda_module.py
parallax_ai/modules/module_interface.py
parallax_ai/modules/switch_module.py
parallax_ai/modules/safeguards/__init__.py
parallax_ai/modules/safeguards/base_module.py
parallax_ai/modules/safeguards/llamaguard_module.py
parallax_ai/modules/safeguards/polyguard_module.py
parallax_ai/modules/safeguards/qwen3guard_module.py
parallax_ai/modules/safeguards/sealguard_module.py
parallax_ai/modules/safeguards/sealionguard_module.py
parallax_ai/modules/safeguards/shieldgemma_module.py
parallax_ai-0.5.1.dist-info/licenses/LICENSE
parallax_ai-0.5.1.dist-info/METADATA
parallax_ai-0.5.1.dist-info/WHEEL
parallax_ai-0.5.1.dist-info/top_level.txt
parallax_ai-0.5.1.dist-info/RECORD
